Metadata-Version: 1.0
Name: getLink
Version: 0.0.1
Summary: A short summary about your package
Home-page: UNKNOWN
Author: Rakesh Bhol
Author-email: rkbhol1101@gmail.com
License: MIT
Platform: UNKNOWN
